vllm_allocator_adaptor_c.abi3.so
vllm_allocator_adaptor/__init__.py
vllm_allocator_adaptor-0.4.3.dist-info/LICENSE
vllm_allocator_adaptor-0.4.3.dist-info/METADATA
vllm_allocator_adaptor-0.4.3.dist-info/WHEEL
vllm_allocator_adaptor-0.4.3.dist-info/top_level.txt
vllm_allocator_adaptor-0.4.3.dist-info/RECORD
