Metadata-Version: 2.1
Name: vllm_allocator_adaptor
Version: 0.4.3
Summary: vLLM Allocator Adaptor (C/CUDA/Python) using callback shims
Requires-Python: >=3.8
License-File: LICENSE
